music_search/__init__.py
music_search/blocks.py
music_search/music_searcher.py
music_search/example/musicSearch.yaml
chatgpt_mirai_qq_bot_music_search-0.3.2.dist-info/LICENSE
chatgpt_mirai_qq_bot_music_search-0.3.2.dist-info/METADATA
chatgpt_mirai_qq_bot_music_search-0.3.2.dist-info/WHEEL
chatgpt_mirai_qq_bot_music_search-0.3.2.dist-info/entry_points.txt
chatgpt_mirai_qq_bot_music_search-0.3.2.dist-info/top_level.txt
chatgpt_mirai_qq_bot_music_search-0.3.2.dist-info/RECORD
